{
  "Main" : {
    "first_name" : {
      "type" : "Text",
      "config" : {
        "label" : "First Name",
        "placeholder" : "first name (e.g. Bill)"
      }
    },
    "last_name" : {
      "type" : "Text",
      "config" : {
        "label" : "Last Name",
        "placeholder" : "last name (e.g. Soward)"
      }
    },
    "email" : {
      "type" : "Text",
      "config" : {
        "label" : "email",
        "placeholder" : "email (e.g. bill@sheltertech.org)"
      }
    },
    "biography" : {
      "type" : "StructuredText",
      "config" : {
        "multi" : "paragraph,preformatted,heading1,heading2,heading3,heading4,heading5,heading6,strong,em,hyperlink,image,embed,list-item,o-list-item,rtl",
        "label" : "Biography"
      }
    },
    "image" : {
      "type" : "Image",
      "config" : {
        "constraint" : { },
        "thumbnails" : [ ],
        "label" : "image"
      }
    }
  }
}
